serializers_v/json/__init__.py
serializers_v/json/json_serializer.py
serializers_v/json/parser.py
serializers_v/src/__init__.py
serializers_v/src/constants.py
serializers_v/src/serializer.py
serializers_v/toml/__init__.py
serializers_v/toml/parser.py
serializers_v/toml/toml_serializer.py
serializers_v/yaml/__init__.py
serializers_v/yaml/yaml_serializer.py
serializers_v-1.2.dist-info/METADATA
serializers_v-1.2.dist-info/WHEEL
serializers_v-1.2.dist-info/top_level.txt
serializers_v-1.2.dist-info/RECORD
